facts_finder/__init__.py
facts_finder/clean.py
facts_finder/inputlog.py
facts_finder/rearrange.py
facts_finder/commons/__init__.py
facts_finder/commons/common.py
facts_finder/generators/__init__.py
facts_finder/generators/cisco_parser.py
facts_finder/generators/device.py
facts_finder/generators/facts_gen.py
facts_finder/generators/juniper_parser.py
facts_finder/generators/merger.py
facts_finder/generators/cisco/__init__.py
facts_finder/generators/cisco/_cmd_parse_arp_table.py
facts_finder/generators/cisco/_cmd_parse_bgp.py
facts_finder/generators/cisco/_cmd_parse_cdp.py
facts_finder/generators/cisco/_cmd_parse_int_description.py
facts_finder/generators/cisco/_cmd_parse_int_status.py
facts_finder/generators/cisco/_cmd_parse_lldp.py
facts_finder/generators/cisco/_cmd_parse_mac_table.py
facts_finder/generators/cisco/_cmd_parse_ospf.py
facts_finder/generators/cisco/_cmd_parse_running_interfaces.py
facts_finder/generators/cisco/_cmd_parse_running_routes.py
facts_finder/generators/cisco/_cmd_parse_running_system.py
facts_finder/generators/cisco/_cmd_parse_running_vrfs.py
facts_finder/generators/cisco/_cmd_parse_version.py
facts_finder/generators/cisco/common.py
facts_finder/generators/commons/__init__.py
facts_finder/generators/commons/generator_commons.py
facts_finder/generators/juniper/__init__.py
facts_finder/generators/juniper/_cmd_parse_arp_table.py
facts_finder/generators/juniper/_cmd_parse_chassis_hardware.py
facts_finder/generators/juniper/_cmd_parse_int_description.py
facts_finder/generators/juniper/_cmd_parse_lldp.py
facts_finder/generators/juniper/_cmd_parse_running.py
facts_finder/generators/juniper/_cmd_parse_running_bgp.py
facts_finder/generators/juniper/_cmd_parse_running_interfaces.py
facts_finder/generators/juniper/_cmd_parse_running_ospf.py
facts_finder/generators/juniper/_cmd_parse_running_routes.py
facts_finder/generators/juniper/_cmd_parse_running_routing_instances.py
facts_finder/generators/juniper/_cmd_parse_running_system.py
facts_finder-0.1.2.dist-info/LICENSE
facts_finder-0.1.2.dist-info/METADATA
facts_finder-0.1.2.dist-info/WHEEL
facts_finder-0.1.2.dist-info/top_level.txt
facts_finder-0.1.2.dist-info/RECORD
