Metadata-Version: 2.1
Name: facts-finder
Version: 0.1.2
Summary: facts_finder for Networking Geeks
Home-page: https://github.com/alias1978/facts_finder
Author: ALIASGAR - ALI
Author-email: aholo2000@gmail.com
Classifier: Programming Language :: Python :: 3
Classifier: License :: OSI Approved :: MIT License
Classifier: Operating System :: OS Independent
Requires-Python: >=3.7
License-File: LICENSE
Requires-Dist: pandas
Requires-Dist: numpy
Requires-Dist: xlrd
Requires-Dist: openpyxl
Requires-Dist: nettoolkit-db
Requires-Dist: nettoolkit-common
Requires-Dist: pyjuniper
Requires-Dist: pynetcrypt
